odoo10_addon_l10n_it_fatturapa_out_rc-10.0.1.1.0-py3.8-nspkg.pth
odoo/addons/l10n_it_fatturapa_out_rc/README.rst
odoo/addons/l10n_it_fatturapa_out_rc/__init__.py
odoo/addons/l10n_it_fatturapa_out_rc/__manifest__.py
odoo/addons/l10n_it_fatturapa_out_rc/i18n/it.po
odoo/addons/l10n_it_fatturapa_out_rc/i18n/l10n_it_fatturapa_out_rc.pot
odoo/addons/l10n_it_fatturapa_out_rc/models/__init__.py
odoo/addons/l10n_it_fatturapa_out_rc/models/account_invoice.py
odoo/addons/l10n_it_fatturapa_out_rc/models/rc_type.py
odoo/addons/l10n_it_fatturapa_out_rc/readme/CONFIGURE.rst
odoo/addons/l10n_it_fatturapa_out_rc/readme/CONTRIBUTORS.rst
odoo/addons/l10n_it_fatturapa_out_rc/readme/DESCRIPTION.rst
odoo/addons/l10n_it_fatturapa_out_rc/static/description/icon.png
odoo/addons/l10n_it_fatturapa_out_rc/static/description/index.html
odoo/addons/l10n_it_fatturapa_out_rc/tests/__init__.py
odoo/addons/l10n_it_fatturapa_out_rc/tests/test_e_invoice_out_rc.py
odoo/addons/l10n_it_fatturapa_out_rc/tests/data/IT10538570960_00002.xml
odoo/addons/l10n_it_fatturapa_out_rc/tests/data/IT10538570960_00003.xml
odoo/addons/l10n_it_fatturapa_out_rc/tests/data/IT10538570960_00004.xml
odoo/addons/l10n_it_fatturapa_out_rc/views/rc_type_views.xml
odoo/addons/l10n_it_fatturapa_out_rc/wizard/__init__.py
odoo/addons/l10n_it_fatturapa_out_rc/wizard/wizard_export_e_invoice.py
odoo10_addon_l10n_it_fatturapa_out_rc-10.0.1.1.0.dist-info/METADATA
odoo10_addon_l10n_it_fatturapa_out_rc-10.0.1.1.0.dist-info/WHEEL
odoo10_addon_l10n_it_fatturapa_out_rc-10.0.1.1.0.dist-info/namespace_packages.txt
odoo10_addon_l10n_it_fatturapa_out_rc-10.0.1.1.0.dist-info/top_level.txt
odoo10_addon_l10n_it_fatturapa_out_rc-10.0.1.1.0.dist-info/RECORD
