Metadata-Version: 2.1
Name: odoo10-addon-l10n-it-fatturapa-out-rc
Version: 10.0.1.1.0
Summary: Integrazione l10n_it_fatturapa_out e l10n_it_reverse_charge
Home-page: https://github.com/OCA/l10n-italy
Author: TAKOBI, Odoo Community Association (OCA)
Author-email: support@odoo-community.org
License: AGPL-3
Platform: UNKNOWN
Classifier: Programming Language :: Python
Classifier: Framework :: Odoo
Classifier: Framework :: Odoo :: 10.0
Classifier: License :: OSI Approved :: GNU Affero General Public License v3
Classifier: Development Status :: 4 - Beta
Requires-Python: ~=2.7
Requires-Dist: odoo10-addon-l10n-it-fatturapa-in
Requires-Dist: odoo10-addon-l10n-it-fatturapa-out
Requires-Dist: odoo10-addon-l10n-it-reverse-charge
Requires-Dist: odoo (<10.1dev,>=10.0)
